ygg.py
ygg_cli-0.1.5.dist-info/METADATA
ygg_cli-0.1.5.dist-info/WHEEL
ygg_cli-0.1.5.dist-info/entry_points.txt
ygg_cli-0.1.5.dist-info/top_level.txt
ygg_cli-0.1.5.dist-info/RECORD
